imgpassgen/__init__.py
imgpassgen/core.py
imgpassgen/exceptions.py
imgpassgen-0.1.1.dist-info/licenses/LICENSE
imgpassgen-0.1.1.dist-info/METADATA
imgpassgen-0.1.1.dist-info/WHEEL
imgpassgen-0.1.1.dist-info/top_level.txt
imgpassgen-0.1.1.dist-info/RECORD
