Metadata-Version: 2.4
Name: imgpassgen
Version: 0.1.1
Summary: Genera contraseñas seguras a partir de imágenes y frases maestras
Author-email: Yeshua Chiliquinga <yeshuachiliquinga@gmail.com>
Project-URL: Homepage, https://github.com/YeshuaChiliquingaAmaya/imgpassgen
Project-URL: Bug Tracker, https://github.com/YeshuaChiliquingaAmaya/imgpassgen/issues
Classifier: Programming Language :: Python :: 3
Classifier: License :: OSI Approved :: GNU General Public License v3 (GPLv3)
Classifier: Operating System :: OS Independent
Classifier: Intended Audience :: Developers
Classifier: Topic :: Security :: Cryptography
Classifier: Topic :: Software Development :: Libraries :: Python Modules
Requires-Python: >=3.7
License-File: LICENSE
Requires-Dist: numpy>=1.21.0
Requires-Dist: opencv-python-headless>=4.5.0
Requires-Dist: cryptography>=3.4.0
Provides-Extra: dev
Requires-Dist: pytest>=6.0; extra == "dev"
Requires-Dist: black>=21.0; extra == "dev"
Requires-Dist: isort>=5.0; extra == "dev"
Dynamic: license-file
Dynamic: requires-python
